toolup/__init__.py
toolup/__main__.py
toolup/dependency.py
toolup/version.py
toolup-0.2.0.dist-info/METADATA
toolup-0.2.0.dist-info/RECORD
toolup-0.2.0.dist-info/WHEEL
toolup-0.2.0.dist-info/entry_points.txt
toolup-0.2.0.dist-info/top_level.txt
