Metadata-Version: 2.1
Name: toolup
Version: 0.2.0
Summary: Convenience package for installing python-based development tools
Home-page: https://github.com/clbarnes/toolup
Author: Chris L. Barnes
Author-email: barnesc@janelia.hhmi.org
License: MIT
Platform: UNKNOWN
Requires-Python: >=3.6.1
Requires-Dist: toml
